armai/__init__.py
armai-0.1.0.dist-info/METADATA
armai-0.1.0.dist-info/WHEEL
armai-0.1.0.dist-info/RECORD
