Metadata-Version: 2.1
Name: ArmAI
Version: 0.1.0
Summary: 0.1.0-a.1
Author: Greyson Lalonde
Author-email: greyson.r.lalonde@gmail.com
Requires-Python: >=3.10,<4.0
Classifier: Programming Language :: Python :: 3
Classifier: Programming Language :: Python :: 3.10
Classifier: Programming Language :: Python :: 3.11
Classifier: Programming Language :: Python :: 3.12
